legaltech_api_client/__init__.py
legaltech_api_client/api/__init__.py
legaltech_api_client/api/claims_activities_list.py
legaltech_api_client/api/claims_create.py
legaltech_api_client/api/claims_retrieve.py
legaltech_api_client/api/customers_create.py
legaltech_api_client/api/products_create.py
legaltech_api_client/api/services_list.py
legaltech_api_client/client.py
legaltech_api_client/models/__init__.py
legaltech_api_client/models/activity.py
legaltech_api_client/models/blank_enum.py
legaltech_api_client/models/case.py
legaltech_api_client/models/claim_create_request.py
legaltech_api_client/models/claim_metadata.py
legaltech_api_client/models/claim_response.py
legaltech_api_client/models/claim_retrieve.py
legaltech_api_client/models/country_enum.py
legaltech_api_client/models/create_product_request.py
legaltech_api_client/models/create_product_response.py
legaltech_api_client/models/create_product_service_request.py
legaltech_api_client/models/current_state_enum.py
legaltech_api_client/models/customer_create_request.py
legaltech_api_client/models/customer_create_response.py
legaltech_api_client/models/product_metadata.py
legaltech_api_client/models/schema_retrieve_format.py
legaltech_api_client/models/schema_retrieve_lang.py
legaltech_api_client/models/schema_retrieve_response_200.py
legaltech_api_client/models/service.py
legaltech_api_client/types.py
legaltech_api_client-1.3.1.dist-info/WHEEL
legaltech_api_client-1.3.1.dist-info/METADATA
legaltech_api_client-1.3.1.dist-info/RECORD
